node_hermes_qt/__init__.py
node_hermes_qt/connection_widget.py
node_hermes_qt/node_manager_widget.py
node_hermes_qt/recent_file_manager.py
node_hermes_qt/widget_manager.py
node_hermes_qt/nodes/__init__.py
node_hermes_qt/nodes/data_explorer_node.py
node_hermes_qt/nodes/data_tracker_node.py
node_hermes_qt/nodes/generic_qt_node.py
node_hermes_qt/nodes/graph_node.py
node_hermes_qt/nodes/histogram_node.py
node_hermes_qt/nodes/node_manager_node.py
node_hermes_qt/nodes/plot_common.py
node_hermes_qt/ui/toolbar.py
node_hermes_qt/ui/toolbar.ui
node_hermes_qt-1.3.2.dist-info/METADATA
node_hermes_qt-1.3.2.dist-info/WHEEL
node_hermes_qt-1.3.2.dist-info/RECORD
