Metadata-Version: 2.4
Name: node-hermes-qt
Version: 1.3.2
Summary: QT interface libary for the Node Hermes project.
Author-email: floris vernieuwe <floris@vernieuwe.eu>
Requires-Python: >=3.10
Requires-Dist: node-hermes-core>=1.3.0
Requires-Dist: pyqtgraph>=0.13.7
Requires-Dist: pyside6-stubs>=6.4.2.0
Requires-Dist: pyside6>=6.8.2.1
Requires-Dist: qt-custom-treewidget>=0.2.1
Requires-Dist: qtpy>=2.4.3
